smqtk_detection/__init__.py
smqtk_detection/_defaults.py
smqtk_detection/detection_element_factory.py
smqtk_detection/exceptions.py
smqtk_detection/impls/__init__.py
smqtk_detection/impls/detect_image_objects/__init__.py
smqtk_detection/impls/detect_image_objects/centernet.py
smqtk_detection/impls/detect_image_objects/random_detector.py
smqtk_detection/impls/detect_image_objects/resnet_frcnn.py
smqtk_detection/impls/detection_element/__init__.py
smqtk_detection/impls/detection_element/memory.py
smqtk_detection/interfaces/__init__.py
smqtk_detection/interfaces/detect_image_objects.py
smqtk_detection/interfaces/detection_element.py
smqtk_detection/interfaces/object_detector.py
smqtk_detection/py.typed
smqtk_detection/utils/__init__.py
smqtk_detection/utils/bbox.py
smqtk_detection-0.23.0.dist-info/LICENSE.txt
smqtk_detection-0.23.0.dist-info/METADATA
smqtk_detection-0.23.0.dist-info/WHEEL
smqtk_detection-0.23.0.dist-info/entry_points.txt
smqtk_detection-0.23.0.dist-info/RECORD
